{
  "type": "object",
  "value": {
    "number": {
      "type": "number",
      "value": 84
    },
    "enrollment-date": {
      "type": "date",
      "value": "2023-12-14T02:33:17.371Z"
    },
    "init-date": {
      "type": "date",
      "value": "2023-12-14T02:33:17.371Z"
    },
    "user-id": {
      "type": "string",
      "value": "66D2Vmw61WFIW1Zew78I"
    },
    "position": {
      "type": "string",
      "value": ""
    },
    "id": {
      "type": "string",
      "value": "f6mVeGcEmK5mctmYjmkq"
    },
    "kind-member": {
      "type": "string",
      "value": "player"
    },
    "team-id": {
      "type": "string",
      "value": "7G1zmfitEwgU0jpuuwtw"
    }
  }
}