{
  "type": "object",
  "value": {
    "enrollment-date": {
      "type": "date",
      "value": "2023-12-13T21:58:39.876Z"
    },
    "init-date": {
      "type": "date",
      "value": "2023-12-13T21:58:39.876Z"
    },
    "user-id": {
      "type": "string",
      "value": "ZejpWiO4vdrh4p97P318"
    },
    "position": {
      "type": "string",
      "value": ""
    },
    "id": {
      "type": "string",
      "value": "FH1rrjklu7TgrBn2qBw5"
    },
    "kind-member": {
      "type": "string",
      "value": "player"
    },
    "team-id": {
      "type": "string",
      "value": "V0pGhKogsLh40OL5zjxR"
    }
  }
}