{
  "type": "object",
  "value": {
    "image": {
      "type": "string",
      "value": ""
    },
    "phone": {
      "type": "string",
      "value": ""
    },
    "roles": {
      "type": "Array",
      "value": [
        {
          "type": "string",
          "value": "OmUGOqmXbey71Uys1Em2"
        }
      ]
    },
    "document": {
      "type": "string",
      "value": "1056128061"
    },
    "alias": {
      "type": "string",
      "value": ""
    },
    "email": {
      "type": "string",
      "value": ""
    },
    "first-name": {
      "type": "string",
      "value": "Jorge"
    },
    "first-last-name": {
      "type": "string",
      "value": "Garzón"
    },
    "second-last-name": {
      "type": "string",
      "value": "Rendón"
    },
    "second-name": {
      "type": "string",
      "value": "Andrés"
    },
    "administration-mode": {
      "type": "string",
      "value": "self-managed"
    }
  }
}