{
  "type": "object",
  "value": {
    "fixture-stage-id": {
      "type": "string",
      "value": "eqZLr9CCppkMEeS40SAN"
    },
    "label": {
      "type": "string",
      "value": "B"
    },
    "order": {
      "type": "number",
      "value": 1
    },
    "id": {
      "type": "string",
      "value": "sRtQVaif7hnY0DPGL2oj"
    },
    "teams": {
      "type": "Array",
      "value": [
        {
          "type": "string",
          "value": "Md8XOXcoD8reUA1HHo2r"
        },
        {
          "type": "string",
          "value": "hwYXcnHDGbZtkGSYvSCZ"
        },
        {
          "type": "string",
          "value": "B06PAq1lbQgLooNc3bbB"
        },
        {
          "type": "string",
          "value": "7G1zmfitEwgU0jpuuwtw"
        },
        {
          "type": "string",
          "value": "1GH3sYLKQJoGev8yoWr3"
        }
      ]
    },
    "positions-table": {
      "type": "object",
      "value": {
        "analized-matches": {
          "type": "Array",
          "value": [
            {
              "type": "string",
              "value": "2TogT0fXPXzduD09rfLC"
            },
            {
              "type": "string",
              "value": "nidCp3vIJwPNzWA4CFRq"
            }
          ]
        },
        "table": {
          "type": "Array",
          "value": [
            {
              "type": "object",
              "value": {
                "stadistics": {
                  "type": "object",
                  "value": {
                    "goals-against-per-match": {
                      "type": "number",
                      "value": 0
                    },
                    "goals-difference": {
                      "type": "number",
                      "value": 4
                    },
                    "lost-matches": {
                      "type": "number",
                      "value": 0
                    },
                    "played-matches": {
                      "type": "number",
                      "value": 1
                    },
                    "fair-play": {
                      "type": "number",
                      "value": 0
                    },
                    "goals-against": {
                      "type": "number",
                      "value": 0
                    },
                    "goals-in-favor": {
                      "type": "number",
                      "value": 4
                    },
                    "won-matches": {
                      "type": "number",
                      "value": 1
                    },
                    "tied-matches": {
                      "type": "number",
                      "value": 0
                    },
                    "points": {
                      "type": "number",
                      "value": 3
                    }
                  }
                },
                "was-by-random": {
                  "type": "boolean",
                  "value": false
                },
                "team-id": {
                  "type": "string",
                  "value": "Md8XOXcoD8reUA1HHo2r"
                }
              }
            },
            {
              "type": "object",
              "value": {
                "stadistics": {
                  "type": "object",
                  "value": {
                    "goals-against-per-match": {
                      "type": "number",
                      "value": 3
                    },
                    "goals-difference": {
                      "type": "number",
                      "value": 3
                    },
                    "lost-matches": {
                      "type": "number",
                      "value": 0
                    },
                    "played-matches": {
                      "type": "number",
                      "value": 1
                    },
                    "fair-play": {
                      "type": "number",
                      "value": 0
                    },
                    "goals-against": {
                      "type": "number",
                      "value": 3
                    },
                    "goals-in-favor": {
                      "type": "number",
                      "value": 6
                    },
                    "won-matches": {
                      "type": "number",
                      "value": 1
                    },
                    "tied-matches": {
                      "type": "number",
                      "value": 0
                    },
                    "points": {
                      "type": "number",
                      "value": 3
                    }
                  }
                },
                "was-by-random": {
                  "type": "boolean",
                  "value": false
                },
                "team-id": {
                  "type": "string",
                  "value": "1GH3sYLKQJoGev8yoWr3"
                }
              }
            },
            {
              "type": "object",
              "value": {
                "stadistics": {
                  "type": "object",
                  "value": {
                    "goals-against-per-match": {
                      "type": "number",
                      "value": 6
                    },
                    "goals-difference": {
                      "type": "number",
                      "value": -3
                    },
                    "lost-matches": {
                      "type": "number",
                      "value": 1
                    },
                    "played-matches": {
                      "type": "number",
                      "value": 1
                    },
                    "fair-play": {
                      "type": "number",
                      "value": 0
                    },
                    "goals-against": {
                      "type": "number",
                      "value": 6
                    },
                    "goals-in-favor": {
                      "type": "number",
                      "value": 3
                    },
                    "won-matches": {
                      "type": "number",
                      "value": 0
                    },
                    "tied-matches": {
                      "type": "number",
                      "value": 0
                    },
                    "points": {
                      "type": "number",
                      "value": 0
                    }
                  }
                },
                "was-by-random": {
                  "type": "boolean",
                  "value": false
                },
                "team-id": {
                  "type": "string",
                  "value": "B06PAq1lbQgLooNc3bbB"
                }
              }
            },
            {
              "type": "object",
              "value": {
                "stadistics": {
                  "type": "object",
                  "value": {
                    "goals-against-per-match": {
                      "type": "number",
                      "value": 4
                    },
                    "goals-difference": {
                      "type": "number",
                      "value": -4
                    },
                    "lost-matches": {
                      "type": "number",
                      "value": 1
                    },
                    "played-matches": {
                      "type": "number",
                      "value": 1
                    },
                    "fair-play": {
                      "type": "number",
                      "value": 0
                    },
                    "goals-against": {
                      "type": "number",
                      "value": 4
                    },
                    "goals-in-favor": {
                      "type": "number",
                      "value": 0
                    },
                    "won-matches": {
                      "type": "number",
                      "value": 0
                    },
                    "tied-matches": {
                      "type": "number",
                      "value": 0
                    },
                    "points": {
                      "type": "number",
                      "value": 0
                    }
                  }
                },
                "was-by-random": {
                  "type": "boolean",
                  "value": false
                },
                "team-id": {
                  "type": "string",
                  "value": "hwYXcnHDGbZtkGSYvSCZ"
                }
              }
            }
          ]
        }
      }
    }
  }
}