{
  "type": "object",
  "value": {
    "number": {
      "type": "number",
      "value": 2
    },
    "init-date": {
      "type": "date",
      "value": "2022-12-01T05:00:00.000Z"
    },
    "user-id": {
      "type": "string",
      "value": "Qy2oFfQ2FadPOSq1oVrU"
    },
    "position": {
      "type": "string",
      "value": ""
    },
    "team-id": {
      "type": "string",
      "value": "mfyVLx7DtCZ1peGE2V39"
    },
    "retirement-date": {
      "type": "date",
      "value": "2023-12-08T12:49:44.174Z"
    },
    "id": {
      "type": "string",
      "value": "7bd65b704a244828a1d0"
    },
    "kind-member": {
      "type": "string",
      "value": "player"
    }
  }
}