{
  "type": "object",
  "value": {
    "city": {
      "type": "string",
      "value": "Bogota"
    },
    "name": {
      "type": "string",
      "value": "Caterpillar Motor B"
    },
    "category": {
      "type": "string",
      "value": "Sub 13"
    },
    "status": {
      "type": "string",
      "value": "enabled"
    },
    "shield": {
      "type": "string",
      "value": "teams/55QmCiGAOIiOO5rjgFfs/brand/shield.png"
    },
    "id": {
      "type": "string",
      "value": "55QmCiGAOIiOO5rjgFfs"
    },
    "mini-shield": {
      "type": "string",
      "value": "teams/55QmCiGAOIiOO5rjgFfs/brand/mini-shield.png"
    }
  }
}