{
  "type": "object",
  "value": {
    "enrollment-date": {
      "type": "date",
      "value": "2023-10-25T02:14:41.167Z"
    },
    "init-date": {
      "type": "date",
      "value": "2023-10-25T02:14:41.167Z"
    },
    "user-id": {
      "type": "string",
      "value": "TFDe4vE3sZRJxVmEhJc2"
    },
    "position": {
      "type": "string",
      "value": ""
    },
    "kind-member": {
      "type": "string",
      "value": "player"
    },
    "team-id": {
      "type": "string",
      "value": "65Q2kTRK5NVhn9rBYgFd"
    }
  }
}