{
  "type": "object",
  "value": {
    "date": {
      "type": "date",
      "value": "2022-12-07T17:30:00.000Z"
    },
    "judge-signature": {
      "type": "string",
      "value": "tournaments/Wl4ZhDEjmAG9iIPSjS4K/fixture-stages/kCGqBvx5XU8mDddXR2PM/groups/b847bd04bf52412ca8ed/matches/0d8fae41a9b841b8b28a/judgeSignature.jpg"
    },
    "group-id": {
      "type": "string",
      "value": "b847bd04bf52412ca8ed"
    },
    "captain-a-signature": {
      "type": "string",
      "value": "tournaments/Wl4ZhDEjmAG9iIPSjS4K/fixture-stages/kCGqBvx5XU8mDddXR2PM/groups/b847bd04bf52412ca8ed/matches/0d8fae41a9b841b8b28a/captainASignature.jpg"
    },
    "team-a-id": {
      "type": "string",
      "value": "DMyyLNT3AYAMEtbtxMvz"
    },
    "team-b-id": {
      "type": "string",
      "value": "SMg6AYs8msQaPXkFfN3W"
    },
    "stadistics": {
      "type": "object",
      "value": {
        "extra-goals-team-a": {
          "type": "object",
          "value": {
            "description": {
              "type": "string",
              "value": ""
            },
            "goals": {
              "type": "number",
              "value": 0
            }
          }
        },
        "team-b": {
          "type": "Array",
          "value": [
            {
              "type": "object",
              "value": {
                "total-goals": {
                  "type": "number",
                  "value": 1
                },
                "member-id": {
                  "type": "string",
                  "value": "8aa74aa8cbb541d0a0ad"
                },
                "yellow-cards": {
                  "type": "Array",
                  "value": []
                },
                "total-yellow-cards": {
                  "type": "number",
                  "value": 0
                },
                "user-id": {
                  "type": "string",
                  "value": "N64NlnE4wRI92BaPsfJC"
                },
                "red-cards": {
                  "type": "Array",
                  "value": []
                },
                "total-red-cards": {
                  "type": "number",
                  "value": 0
                },
                "goals": {
                  "type": "Array",
                  "value": []
                }
              }
            }
          ]
        },
        "extra-goals-team-b": {
          "type": "object",
          "value": {
            "description": {
              "type": "string",
              "value": ""
            },
            "goals": {
              "type": "number",
              "value": 0
            }
          }
        },
        "team-a": {
          "type": "Array",
          "value": [
            {
              "type": "object",
              "value": {
                "total-goals": {
                  "type": "number",
                  "value": 1
                },
                "member-id": {
                  "type": "string",
                  "value": "cd8748da916c4a48bf47"
                },
                "yellow-cards": {
                  "type": "Array",
                  "value": []
                },
                "total-yellow-cards": {
                  "type": "number",
                  "value": 0
                },
                "user-id": {
                  "type": "string",
                  "value": "K9CRHlOneYKVvcdpOgrq"
                },
                "red-cards": {
                  "type": "Array",
                  "value": []
                },
                "total-red-cards": {
                  "type": "number",
                  "value": 0
                },
                "goals": {
                  "type": "Array",
                  "value": []
                }
              }
            },
            {
              "type": "object",
              "value": {
                "total-goals": {
                  "type": "number",
                  "value": 1
                },
                "member-id": {
                  "type": "string",
                  "value": "7a7e031a63c8434c8cc5"
                },
                "yellow-cards": {
                  "type": "Array",
                  "value": []
                },
                "total-yellow-cards": {
                  "type": "number",
                  "value": 0
                },
                "user-id": {
                  "type": "string",
                  "value": "04MTsQkt3O6ycNJ1QQMj"
                },
                "red-cards": {
                  "type": "Array",
                  "value": []
                },
                "total-red-cards": {
                  "type": "number",
                  "value": 0
                },
                "goals": {
                  "type": "Array",
                  "value": []
                }
              }
            },
            {
              "type": "object",
              "value": {
                "total-goals": {
                  "type": "number",
                  "value": 1
                },
                "member-id": {
                  "type": "string",
                  "value": "bc514a7ebc514ff69d62"
                },
                "yellow-cards": {
                  "type": "Array",
                  "value": []
                },
                "total-yellow-cards": {
                  "type": "number",
                  "value": 0
                },
                "user-id": {
                  "type": "string",
                  "value": "j1Mrt5wFq8wOdT7uM64S"
                },
                "red-cards": {
                  "type": "Array",
                  "value": []
                },
                "total-red-cards": {
                  "type": "number",
                  "value": 0
                },
                "goals": {
                  "type": "Array",
                  "value": []
                }
              }
            }
          ]
        }
      }
    },
    "captain-b-signature": {
      "type": "string",
      "value": "tournaments/Wl4ZhDEjmAG9iIPSjS4K/fixture-stages/kCGqBvx5XU8mDddXR2PM/groups/b847bd04bf52412ca8ed/matches/0d8fae41a9b841b8b28a/captainBSignature.jpg"
    },
    "score": {
      "type": "object",
      "value": {
        "team-b": {
          "type": "number",
          "value": 1
        },
        "team-a": {
          "type": "number",
          "value": 3
        }
      }
    },
    "playground": {
      "type": "object",
      "value": {
        "name": {
          "type": "string",
          "value": "Cancha 1"
        }
      }
    },
    "location-id": {
      "type": "string",
      "value": "IE4qNsCVvLcDmAb6dRc3"
    },
    "player-form": {
      "type": "object",
      "value": {
        "team-b": {
          "type": "Array",
          "value": [
            {
              "type": "string",
              "value": "3ebacf837011423fbdc2"
            },
            {
              "type": "string",
              "value": "20f796cee29e4bdcb19f"
            },
            {
              "type": "string",
              "value": "c4ca389a7cb6425192e7"
            },
            {
              "type": "string",
              "value": "bec5ac1d4f9f4d60b46a"
            },
            {
              "type": "string",
              "value": "fc5d74a9692d42799276"
            },
            {
              "type": "string",
              "value": "0b2c7a4cdc2b4acba212"
            },
            {
              "type": "string",
              "value": "5f5c1ba782494fd3a610"
            },
            {
              "type": "string",
              "value": "8aa74aa8cbb541d0a0ad"
            },
            {
              "type": "string",
              "value": "506b289ef4a24aa99d5f"
            },
            {
              "type": "string",
              "value": "d21f5c5ff82a4cda95c7"
            },
            {
              "type": "string",
              "value": "194de3110c57423bbc40"
            },
            {
              "type": "string",
              "value": "fe8c40fa1551412e8b11"
            }
          ]
        },
        "team-a": {
          "type": "Array",
          "value": [
            {
              "type": "string",
              "value": "e28b9d2b8f4a4e81a40a"
            },
            {
              "type": "string",
              "value": "e961fc5520154dd29608"
            },
            {
              "type": "string",
              "value": "4506ecb359f34bb4a1d3"
            },
            {
              "type": "string",
              "value": "4f5c534407dc4248851f"
            },
            {
              "type": "string",
              "value": "36ac7e868b324bbd837d"
            },
            {
              "type": "string",
              "value": "ef841d71b7db42b19460"
            },
            {
              "type": "string",
              "value": "2a904ebe568440308f01"
            },
            {
              "type": "string",
              "value": "7425721e7cda4f4db06e"
            },
            {
              "type": "string",
              "value": "6b7ff8245d3f4d51adf3"
            },
            {
              "type": "string",
              "value": "cd8748da916c4a48bf47"
            },
            {
              "type": "string",
              "value": "7a7e031a63c8434c8cc5"
            },
            {
              "type": "string",
              "value": "d7c46607229f483e98a6"
            },
            {
              "type": "string",
              "value": "15a0b7ac090c4178a510"
            },
            {
              "type": "string",
              "value": "d34674666c0a426db8d9"
            },
            {
              "type": "string",
              "value": "bc514a7ebc514ff69d62"
            }
          ]
        }
      }
    },
    "status": {
      "type": "string",
      "value": "completed"
    }
  }
}