{
  "type": "object",
  "value": {
    "level": {
      "type": "number",
      "value": 2
    },
    "key": {
      "type": "number",
      "value": 3
    },
    "id": {
      "type": "string",
      "value": "VGnJd3bbMHXlexpxK3Ol"
    },
    "match": {
      "type": "object",
      "value": {
        "date": {
          "type": "date",
          "value": "2022-12-06T16:30:00.000Z"
        },
        "judge-signature": {
          "type": "string",
          "value": "tournaments/uVvaemEgV5nWAj3OBcIj/main-draw/VGnJd3bbMHXlexpxK3Ol/judgeSignature.jpg"
        },
        "captain-a-signature": {
          "type": "string",
          "value": "tournaments/uVvaemEgV5nWAj3OBcIj/main-draw/VGnJd3bbMHXlexpxK3Ol/captainASignature.jpg"
        },
        "completed": {
          "type": "boolean",
          "value": true
        },
        "stadistics": {
          "type": "object",
          "value": {
            "extra-goals-team-a": {
              "type": "object",
              "value": {
                "description": {
                  "type": "string",
                  "value": ""
                },
                "goals": {
                  "type": "number",
                  "value": 0
                }
              }
            },
            "team-b": {
              "type": "Array",
              "value": [
                {
                  "type": "object",
                  "value": {
                    "total-goals": {
                      "type": "number",
                      "value": 1
                    },
                    "yellow-cards": {
                      "type": "Array",
                      "value": []
                    },
                    "total-yellow-cards": {
                      "type": "number",
                      "value": 1
                    },
                    "red-cards": {
                      "type": "Array",
                      "value": []
                    },
                    "total-red-cards": {
                      "type": "number",
                      "value": 0
                    },
                    "goals": {
                      "type": "Array",
                      "value": []
                    },
                    "player": {
                      "type": "reference",
                      "value": "users/fbIbC0tLIQ9clfsBtPoM"
                    }
                  }
                },
                {
                  "type": "object",
                  "value": {
                    "total-goals": {
                      "type": "number",
                      "value": 0
                    },
                    "yellow-cards": {
                      "type": "Array",
                      "value": []
                    },
                    "total-yellow-cards": {
                      "type": "number",
                      "value": 0
                    },
                    "red-cards": {
                      "type": "Array",
                      "value": []
                    },
                    "total-red-cards": {
                      "type": "number",
                      "value": 0
                    },
                    "goals": {
                      "type": "Array",
                      "value": []
                    },
                    "player": {
                      "type": "reference",
                      "value": "users/mVrz6hztH50pzpSXBI52"
                    }
                  }
                },
                {
                  "type": "object",
                  "value": {
                    "total-goals": {
                      "type": "number",
                      "value": 0
                    },
                    "yellow-cards": {
                      "type": "Array",
                      "value": []
                    },
                    "total-yellow-cards": {
                      "type": "number",
                      "value": 0
                    },
                    "red-cards": {
                      "type": "Array",
                      "value": []
                    },
                    "total-red-cards": {
                      "type": "number",
                      "value": 0
                    },
                    "goals": {
                      "type": "Array",
                      "value": []
                    },
                    "player": {
                      "type": "reference",
                      "value": "users/vkSONFNqUBYfBJUQmKfc"
                    }
                  }
                },
                {
                  "type": "object",
                  "value": {
                    "total-goals": {
                      "type": "number",
                      "value": 0
                    },
                    "yellow-cards": {
                      "type": "Array",
                      "value": []
                    },
                    "total-yellow-cards": {
                      "type": "number",
                      "value": 0
                    },
                    "red-cards": {
                      "type": "Array",
                      "value": []
                    },
                    "total-red-cards": {
                      "type": "number",
                      "value": 0
                    },
                    "goals": {
                      "type": "Array",
                      "value": []
                    },
                    "player": {
                      "type": "reference",
                      "value": "users/QRneTz8ZwuddVM0kzHQY"
                    }
                  }
                },
                {
                  "type": "object",
                  "value": {
                    "total-goals": {
                      "type": "number",
                      "value": 1
                    },
                    "yellow-cards": {
                      "type": "Array",
                      "value": []
                    },
                    "total-yellow-cards": {
                      "type": "number",
                      "value": 1
                    },
                    "red-cards": {
                      "type": "Array",
                      "value": []
                    },
                    "total-red-cards": {
                      "type": "number",
                      "value": 0
                    },
                    "goals": {
                      "type": "Array",
                      "value": []
                    },
                    "player": {
                      "type": "reference",
                      "value": "users/RX6SKQZ1WhPzXHtbPTZG"
                    }
                  }
                },
                {
                  "type": "object",
                  "value": {
                    "total-goals": {
                      "type": "number",
                      "value": 0
                    },
                    "yellow-cards": {
                      "type": "Array",
                      "value": []
                    },
                    "total-yellow-cards": {
                      "type": "number",
                      "value": 0
                    },
                    "red-cards": {
                      "type": "Array",
                      "value": []
                    },
                    "total-red-cards": {
                      "type": "number",
                      "value": 0
                    },
                    "goals": {
                      "type": "Array",
                      "value": []
                    },
                    "player": {
                      "type": "reference",
                      "value": "users/eg22sxGllQcd2yk8940h"
                    }
                  }
                },
                {
                  "type": "object",
                  "value": {
                    "total-goals": {
                      "type": "number",
                      "value": 0
                    },
                    "yellow-cards": {
                      "type": "Array",
                      "value": []
                    },
                    "total-yellow-cards": {
                      "type": "number",
                      "value": 0
                    },
                    "red-cards": {
                      "type": "Array",
                      "value": []
                    },
                    "total-red-cards": {
                      "type": "number",
                      "value": 0
                    },
                    "goals": {
                      "type": "Array",
                      "value": []
                    },
                    "player": {
                      "type": "reference",
                      "value": "users/SjupBV4kUp4k2yhbuCC5"
                    }
                  }
                },
                {
                  "type": "object",
                  "value": {
                    "total-goals": {
                      "type": "number",
                      "value": 0
                    },
                    "yellow-cards": {
                      "type": "Array",
                      "value": []
                    },
                    "total-yellow-cards": {
                      "type": "number",
                      "value": 0
                    },
                    "red-cards": {
                      "type": "Array",
                      "value": []
                    },
                    "total-red-cards": {
                      "type": "number",
                      "value": 0
                    },
                    "goals": {
                      "type": "Array",
                      "value": []
                    },
                    "player": {
                      "type": "reference",
                      "value": "users/gtGOncuXtOjfzkbr8FvE"
                    }
                  }
                },
                {
                  "type": "object",
                  "value": {
                    "total-goals": {
                      "type": "number",
                      "value": 0
                    },
                    "yellow-cards": {
                      "type": "Array",
                      "value": []
                    },
                    "total-yellow-cards": {
                      "type": "number",
                      "value": 0
                    },
                    "red-cards": {
                      "type": "Array",
                      "value": []
                    },
                    "total-red-cards": {
                      "type": "number",
                      "value": 0
                    },
                    "goals": {
                      "type": "Array",
                      "value": []
                    },
                    "player": {
                      "type": "reference",
                      "value": "users/l7o5dmdH7jcEmsLwcwFM"
                    }
                  }
                },
                {
                  "type": "object",
                  "value": {
                    "total-goals": {
                      "type": "number",
                      "value": 0
                    },
                    "yellow-cards": {
                      "type": "Array",
                      "value": []
                    },
                    "total-yellow-cards": {
                      "type": "number",
                      "value": 0
                    },
                    "red-cards": {
                      "type": "Array",
                      "value": []
                    },
                    "total-red-cards": {
                      "type": "number",
                      "value": 0
                    },
                    "goals": {
                      "type": "Array",
                      "value": []
                    },
                    "player": {
                      "type": "reference",
                      "value": "users/B6UzNtMG3t7tRSpjydnE"
                    }
                  }
                },
                {
                  "type": "object",
                  "value": {
                    "total-goals": {
                      "type": "number",
                      "value": 0
                    },
                    "yellow-cards": {
                      "type": "Array",
                      "value": []
                    },
                    "total-yellow-cards": {
                      "type": "number",
                      "value": 0
                    },
                    "red-cards": {
                      "type": "Array",
                      "value": []
                    },
                    "total-red-cards": {
                      "type": "number",
                      "value": 0
                    },
                    "goals": {
                      "type": "Array",
                      "value": []
                    },
                    "player": {
                      "type": "reference",
                      "value": "users/R5K1sUtFafI1MYtYMz6h"
                    }
                  }
                },
                {
                  "type": "object",
                  "value": {
                    "total-goals": {
                      "type": "number",
                      "value": 0
                    },
                    "yellow-cards": {
                      "type": "Array",
                      "value": []
                    },
                    "total-yellow-cards": {
                      "type": "number",
                      "value": 1
                    },
                    "red-cards": {
                      "type": "Array",
                      "value": []
                    },
                    "total-red-cards": {
                      "type": "number",
                      "value": 0
                    },
                    "goals": {
                      "type": "Array",
                      "value": []
                    },
                    "player": {
                      "type": "reference",
                      "value": "users/NVemNjWZAX5a7m4INAUd"
                    }
                  }
                },
                {
                  "type": "object",
                  "value": {
                    "total-goals": {
                      "type": "number",
                      "value": 0
                    },
                    "yellow-cards": {
                      "type": "Array",
                      "value": []
                    },
                    "total-yellow-cards": {
                      "type": "number",
                      "value": 0
                    },
                    "red-cards": {
                      "type": "Array",
                      "value": []
                    },
                    "total-red-cards": {
                      "type": "number",
                      "value": 0
                    },
                    "goals": {
                      "type": "Array",
                      "value": []
                    },
                    "player": {
                      "type": "reference",
                      "value": "users/7eT2dnASjx7YkcV2xcKv"
                    }
                  }
                },
                {
                  "type": "object",
                  "value": {
                    "total-goals": {
                      "type": "number",
                      "value": 0
                    },
                    "yellow-cards": {
                      "type": "Array",
                      "value": []
                    },
                    "total-yellow-cards": {
                      "type": "number",
                      "value": 0
                    },
                    "red-cards": {
                      "type": "Array",
                      "value": []
                    },
                    "total-red-cards": {
                      "type": "number",
                      "value": 0
                    },
                    "goals": {
                      "type": "Array",
                      "value": []
                    },
                    "player": {
                      "type": "reference",
                      "value": "users/aQgnONV2Cnrt3cJAnQcU"
                    }
                  }
                },
                {
                  "type": "object",
                  "value": {
                    "total-goals": {
                      "type": "number",
                      "value": 0
                    },
                    "yellow-cards": {
                      "type": "Array",
                      "value": []
                    },
                    "total-yellow-cards": {
                      "type": "number",
                      "value": 0
                    },
                    "red-cards": {
                      "type": "Array",
                      "value": []
                    },
                    "total-red-cards": {
                      "type": "number",
                      "value": 0
                    },
                    "goals": {
                      "type": "Array",
                      "value": []
                    },
                    "player": {
                      "type": "reference",
                      "value": "users/YQouu8pttwcVOHbJCDOd"
                    }
                  }
                },
                {
                  "type": "object",
                  "value": {
                    "total-goals": {
                      "type": "number",
                      "value": 0
                    },
                    "yellow-cards": {
                      "type": "Array",
                      "value": []
                    },
                    "total-yellow-cards": {
                      "type": "number",
                      "value": 0
                    },
                    "red-cards": {
                      "type": "Array",
                      "value": []
                    },
                    "total-red-cards": {
                      "type": "number",
                      "value": 0
                    },
                    "goals": {
                      "type": "Array",
                      "value": []
                    },
                    "player": {
                      "type": "reference",
                      "value": "users/TxphBrC665GkBuZDpGXt"
                    }
                  }
                },
                {
                  "type": "object",
                  "value": {
                    "total-goals": {
                      "type": "number",
                      "value": 0
                    },
                    "yellow-cards": {
                      "type": "Array",
                      "value": []
                    },
                    "total-yellow-cards": {
                      "type": "number",
                      "value": 0
                    },
                    "red-cards": {
                      "type": "Array",
                      "value": []
                    },
                    "total-red-cards": {
                      "type": "number",
                      "value": 0
                    },
                    "goals": {
                      "type": "Array",
                      "value": []
                    },
                    "player": {
                      "type": "reference",
                      "value": "users/3obFpjrwhA8zsWUazEDA"
                    }
                  }
                },
                {
                  "type": "object",
                  "value": {
                    "total-goals": {
                      "type": "number",
                      "value": 0
                    },
                    "yellow-cards": {
                      "type": "Array",
                      "value": []
                    },
                    "total-yellow-cards": {
                      "type": "number",
                      "value": 0
                    },
                    "red-cards": {
                      "type": "Array",
                      "value": []
                    },
                    "total-red-cards": {
                      "type": "number",
                      "value": 0
                    },
                    "goals": {
                      "type": "Array",
                      "value": []
                    },
                    "player": {
                      "type": "reference",
                      "value": "users/rI5NFbC6BxtzmCyQWyGo"
                    }
                  }
                }
              ]
            },
            "extra-goals-team-b": {
              "type": "object",
              "value": {
                "description": {
                  "type": "string",
                  "value": ""
                },
                "goals": {
                  "type": "number",
                  "value": 0
                }
              }
            },
            "team-a": {
              "type": "Array",
              "value": [
                {
                  "type": "object",
                  "value": {
                    "total-goals": {
                      "type": "number",
                      "value": 0
                    },
                    "yellow-cards": {
                      "type": "Array",
                      "value": []
                    },
                    "total-yellow-cards": {
                      "type": "number",
                      "value": 0
                    },
                    "red-cards": {
                      "type": "Array",
                      "value": []
                    },
                    "total-red-cards": {
                      "type": "number",
                      "value": 0
                    },
                    "goals": {
                      "type": "Array",
                      "value": []
                    },
                    "player": {
                      "type": "reference",
                      "value": "users/cwlfAD8EWaH1WBGTFlvB"
                    }
                  }
                },
                {
                  "type": "object",
                  "value": {
                    "total-goals": {
                      "type": "number",
                      "value": 0
                    },
                    "yellow-cards": {
                      "type": "Array",
                      "value": []
                    },
                    "total-yellow-cards": {
                      "type": "number",
                      "value": 0
                    },
                    "red-cards": {
                      "type": "Array",
                      "value": []
                    },
                    "total-red-cards": {
                      "type": "number",
                      "value": 0
                    },
                    "goals": {
                      "type": "Array",
                      "value": []
                    },
                    "player": {
                      "type": "reference",
                      "value": "users/vrQDWgs8q4OyUUIRJM0g"
                    }
                  }
                },
                {
                  "type": "object",
                  "value": {
                    "total-goals": {
                      "type": "number",
                      "value": 0
                    },
                    "yellow-cards": {
                      "type": "Array",
                      "value": []
                    },
                    "total-yellow-cards": {
                      "type": "number",
                      "value": 0
                    },
                    "red-cards": {
                      "type": "Array",
                      "value": []
                    },
                    "total-red-cards": {
                      "type": "number",
                      "value": 0
                    },
                    "goals": {
                      "type": "Array",
                      "value": []
                    },
                    "player": {
                      "type": "reference",
                      "value": "users/4FVIbaU2qK3lz4L33Ky3"
                    }
                  }
                },
                {
                  "type": "object",
                  "value": {
                    "total-goals": {
                      "type": "number",
                      "value": 2
                    },
                    "yellow-cards": {
                      "type": "Array",
                      "value": []
                    },
                    "total-yellow-cards": {
                      "type": "number",
                      "value": 1
                    },
                    "red-cards": {
                      "type": "Array",
                      "value": []
                    },
                    "total-red-cards": {
                      "type": "number",
                      "value": 0
                    },
                    "goals": {
                      "type": "Array",
                      "value": []
                    },
                    "player": {
                      "type": "reference",
                      "value": "users/P6ktl6rjmQqyreZQGLgd"
                    }
                  }
                },
                {
                  "type": "object",
                  "value": {
                    "total-goals": {
                      "type": "object",
                      "value": {}
                    },
                    "yellow-cards": {
                      "type": "Array",
                      "value": []
                    },
                    "total-yellow-cards": {
                      "type": "number",
                      "value": 0
                    },
                    "red-cards": {
                      "type": "Array",
                      "value": []
                    },
                    "total-red-cards": {
                      "type": "number",
                      "value": 0
                    },
                    "goals": {
                      "type": "Array",
                      "value": []
                    },
                    "player": {
                      "type": "reference",
                      "value": "users/2i1ntK7g3IulALaR44pF"
                    }
                  }
                },
                {
                  "type": "object",
                  "value": {
                    "total-goals": {
                      "type": "number",
                      "value": 0
                    },
                    "yellow-cards": {
                      "type": "Array",
                      "value": []
                    },
                    "total-yellow-cards": {
                      "type": "number",
                      "value": 1
                    },
                    "red-cards": {
                      "type": "Array",
                      "value": []
                    },
                    "total-red-cards": {
                      "type": "number",
                      "value": 0
                    },
                    "goals": {
                      "type": "Array",
                      "value": []
                    },
                    "player": {
                      "type": "reference",
                      "value": "users/xRyTbKiItimhkGslfWhx"
                    }
                  }
                },
                {
                  "type": "object",
                  "value": {
                    "total-goals": {
                      "type": "number",
                      "value": 0
                    },
                    "yellow-cards": {
                      "type": "Array",
                      "value": []
                    },
                    "total-yellow-cards": {
                      "type": "number",
                      "value": 0
                    },
                    "red-cards": {
                      "type": "Array",
                      "value": []
                    },
                    "total-red-cards": {
                      "type": "number",
                      "value": 0
                    },
                    "goals": {
                      "type": "Array",
                      "value": []
                    },
                    "player": {
                      "type": "reference",
                      "value": "users/U0hDeeWlorOzaICsOyh5"
                    }
                  }
                },
                {
                  "type": "object",
                  "value": {
                    "total-goals": {
                      "type": "number",
                      "value": 0
                    },
                    "yellow-cards": {
                      "type": "Array",
                      "value": []
                    },
                    "total-yellow-cards": {
                      "type": "number",
                      "value": 1
                    },
                    "red-cards": {
                      "type": "Array",
                      "value": []
                    },
                    "total-red-cards": {
                      "type": "number",
                      "value": 0
                    },
                    "goals": {
                      "type": "Array",
                      "value": []
                    },
                    "player": {
                      "type": "reference",
                      "value": "users/Gl4KeQseKlx8vTkr5FsH"
                    }
                  }
                },
                {
                  "type": "object",
                  "value": {
                    "total-goals": {
                      "type": "number",
                      "value": 0
                    },
                    "yellow-cards": {
                      "type": "Array",
                      "value": []
                    },
                    "total-yellow-cards": {
                      "type": "number",
                      "value": 0
                    },
                    "red-cards": {
                      "type": "Array",
                      "value": []
                    },
                    "total-red-cards": {
                      "type": "number",
                      "value": 0
                    },
                    "goals": {
                      "type": "Array",
                      "value": []
                    },
                    "player": {
                      "type": "reference",
                      "value": "users/b8xWUObC6hroaCG9tXF8"
                    }
                  }
                },
                {
                  "type": "object",
                  "value": {
                    "total-goals": {
                      "type": "number",
                      "value": 0
                    },
                    "yellow-cards": {
                      "type": "Array",
                      "value": []
                    },
                    "total-yellow-cards": {
                      "type": "number",
                      "value": 0
                    },
                    "red-cards": {
                      "type": "Array",
                      "value": []
                    },
                    "total-red-cards": {
                      "type": "number",
                      "value": 0
                    },
                    "goals": {
                      "type": "Array",
                      "value": []
                    },
                    "player": {
                      "type": "reference",
                      "value": "users/aWH7PW2TQlfRcz2JVqUt"
                    }
                  }
                },
                {
                  "type": "object",
                  "value": {
                    "total-goals": {
                      "type": "number",
                      "value": 2
                    },
                    "yellow-cards": {
                      "type": "Array",
                      "value": []
                    },
                    "total-yellow-cards": {
                      "type": "number",
                      "value": 0
                    },
                    "red-cards": {
                      "type": "Array",
                      "value": []
                    },
                    "total-red-cards": {
                      "type": "number",
                      "value": 0
                    },
                    "goals": {
                      "type": "Array",
                      "value": []
                    },
                    "player": {
                      "type": "reference",
                      "value": "users/wbMYtNCpwBTfonCznq0h"
                    }
                  }
                },
                {
                  "type": "object",
                  "value": {
                    "total-goals": {
                      "type": "number",
                      "value": 0
                    },
                    "yellow-cards": {
                      "type": "Array",
                      "value": []
                    },
                    "total-yellow-cards": {
                      "type": "number",
                      "value": 0
                    },
                    "red-cards": {
                      "type": "Array",
                      "value": []
                    },
                    "total-red-cards": {
                      "type": "number",
                      "value": 0
                    },
                    "goals": {
                      "type": "Array",
                      "value": []
                    },
                    "player": {
                      "type": "reference",
                      "value": "users/C4sxphVmb3XaDc2iGskq"
                    }
                  }
                },
                {
                  "type": "object",
                  "value": {
                    "total-goals": {
                      "type": "number",
                      "value": 0
                    },
                    "yellow-cards": {
                      "type": "Array",
                      "value": []
                    },
                    "total-yellow-cards": {
                      "type": "number",
                      "value": 0
                    },
                    "red-cards": {
                      "type": "Array",
                      "value": []
                    },
                    "total-red-cards": {
                      "type": "number",
                      "value": 0
                    },
                    "goals": {
                      "type": "Array",
                      "value": []
                    },
                    "player": {
                      "type": "reference",
                      "value": "users/zaBMHUReBXNOp85bBPLC"
                    }
                  }
                },
                {
                  "type": "object",
                  "value": {
                    "total-goals": {
                      "type": "number",
                      "value": 0
                    },
                    "yellow-cards": {
                      "type": "Array",
                      "value": []
                    },
                    "total-yellow-cards": {
                      "type": "number",
                      "value": 0
                    },
                    "red-cards": {
                      "type": "Array",
                      "value": []
                    },
                    "total-red-cards": {
                      "type": "number",
                      "value": 0
                    },
                    "goals": {
                      "type": "Array",
                      "value": []
                    },
                    "player": {
                      "type": "reference",
                      "value": "users/XHWfbRD2JCxq59vUf1j1"
                    }
                  }
                },
                {
                  "type": "object",
                  "value": {
                    "total-goals": {
                      "type": "number",
                      "value": 0
                    },
                    "yellow-cards": {
                      "type": "Array",
                      "value": []
                    },
                    "total-yellow-cards": {
                      "type": "number",
                      "value": 0
                    },
                    "red-cards": {
                      "type": "Array",
                      "value": []
                    },
                    "total-red-cards": {
                      "type": "number",
                      "value": 0
                    },
                    "goals": {
                      "type": "Array",
                      "value": []
                    },
                    "player": {
                      "type": "reference",
                      "value": "users/sqXtko2k5VNsgCp5v3e1"
                    }
                  }
                },
                {
                  "type": "object",
                  "value": {
                    "total-goals": {
                      "type": "number",
                      "value": 0
                    },
                    "yellow-cards": {
                      "type": "Array",
                      "value": []
                    },
                    "total-yellow-cards": {
                      "type": "number",
                      "value": 0
                    },
                    "red-cards": {
                      "type": "Array",
                      "value": []
                    },
                    "total-red-cards": {
                      "type": "number",
                      "value": 0
                    },
                    "goals": {
                      "type": "Array",
                      "value": []
                    },
                    "player": {
                      "type": "reference",
                      "value": "users/MP5vAVwJagGDbJ8s2sNO"
                    }
                  }
                },
                {
                  "type": "object",
                  "value": {
                    "total-goals": {
                      "type": "number",
                      "value": 0
                    },
                    "yellow-cards": {
                      "type": "Array",
                      "value": []
                    },
                    "total-yellow-cards": {
                      "type": "number",
                      "value": 0
                    },
                    "red-cards": {
                      "type": "Array",
                      "value": []
                    },
                    "total-red-cards": {
                      "type": "number",
                      "value": 0
                    },
                    "goals": {
                      "type": "Array",
                      "value": []
                    },
                    "player": {
                      "type": "reference",
                      "value": "users/SXGvhDcMnthdI34vxwR7"
                    }
                  }
                }
              ]
            }
          }
        },
        "captain-b-signature": {
          "type": "string",
          "value": "tournaments/uVvaemEgV5nWAj3OBcIj/main-draw/VGnJd3bbMHXlexpxK3Ol/captainBSignature.jpg"
        },
        "score": {
          "type": "object",
          "value": {
            "team-b": {
              "type": "number",
              "value": 2
            },
            "team-a": {
              "type": "number",
              "value": 4
            }
          }
        },
        "observations": {
          "type": "string",
          "value": "Expulsado Dt de equipo mora mora.por utilizar vocabulario humillante (descarada ,atrevida).cuando atendió a un jugador dentro del terreno.ingresando sin autorización.\nNota .pasado unos minutos.regresa al camerino a mostrar el pecho con laceraciones de un jugador distinto al que choco.supestamente con el portero. Dónde el juez dice que es choque fortuito y gritando repetidamente descarada.igualmemte la delegada del equipo gritaba descarada nos robó el partido.y todos los jugadores y el cuerpo técnico del mismo equipo a irrespetar la organización, y la coordinadora tuvo que sacarlos del escenario deportivo "
        },
        "playground": {
          "type": "object",
          "value": {
            "name": {
              "type": "string",
              "value": "Cancha 1"
            }
          }
        },
        "location": {
          "type": "reference",
          "value": "locations/P8sds0iDJaem6eVMJocY"
        },
        "team-b": {
          "type": "reference",
          "value": "teams/AcHFPT44JSB9TnLtzAfu"
        },
        "team-a": {
          "type": "reference",
          "value": "teams/C0CKonLcaU1X8LcMslFl"
        },
        "player-form": {
          "type": "object",
          "value": {
            "team-b": {
              "type": "Array",
              "value": [
                {
                  "type": "reference",
                  "value": "users/l7o5dmdH7jcEmsLwcwFM"
                },
                {
                  "type": "reference",
                  "value": "users/RX6SKQZ1WhPzXHtbPTZG"
                },
                {
                  "type": "reference",
                  "value": "users/aQgnONV2Cnrt3cJAnQcU"
                },
                {
                  "type": "reference",
                  "value": "users/gtGOncuXtOjfzkbr8FvE"
                },
                {
                  "type": "reference",
                  "value": "users/mVrz6hztH50pzpSXBI52"
                },
                {
                  "type": "reference",
                  "value": "users/7eT2dnASjx7YkcV2xcKv"
                },
                {
                  "type": "reference",
                  "value": "users/TxphBrC665GkBuZDpGXt"
                },
                {
                  "type": "reference",
                  "value": "users/QRneTz8ZwuddVM0kzHQY"
                },
                {
                  "type": "reference",
                  "value": "users/fbIbC0tLIQ9clfsBtPoM"
                },
                {
                  "type": "reference",
                  "value": "users/3obFpjrwhA8zsWUazEDA"
                },
                {
                  "type": "reference",
                  "value": "users/R5K1sUtFafI1MYtYMz6h"
                },
                {
                  "type": "reference",
                  "value": "users/B6UzNtMG3t7tRSpjydnE"
                },
                {
                  "type": "reference",
                  "value": "users/YQouu8pttwcVOHbJCDOd"
                },
                {
                  "type": "reference",
                  "value": "users/vkSONFNqUBYfBJUQmKfc"
                },
                {
                  "type": "reference",
                  "value": "users/eg22sxGllQcd2yk8940h"
                },
                {
                  "type": "reference",
                  "value": "users/SjupBV4kUp4k2yhbuCC5"
                },
                {
                  "type": "reference",
                  "value": "users/rI5NFbC6BxtzmCyQWyGo"
                }
              ]
            },
            "team-a": {
              "type": "Array",
              "value": [
                {
                  "type": "reference",
                  "value": "users/XHWfbRD2JCxq59vUf1j1"
                },
                {
                  "type": "reference",
                  "value": "users/cwlfAD8EWaH1WBGTFlvB"
                },
                {
                  "type": "reference",
                  "value": "users/b8xWUObC6hroaCG9tXF8"
                },
                {
                  "type": "reference",
                  "value": "users/xRyTbKiItimhkGslfWhx"
                },
                {
                  "type": "reference",
                  "value": "users/4FVIbaU2qK3lz4L33Ky3"
                },
                {
                  "type": "reference",
                  "value": "users/2i1ntK7g3IulALaR44pF"
                },
                {
                  "type": "reference",
                  "value": "users/P6ktl6rjmQqyreZQGLgd"
                },
                {
                  "type": "reference",
                  "value": "users/U0hDeeWlorOzaICsOyh5"
                },
                {
                  "type": "reference",
                  "value": "users/aWH7PW2TQlfRcz2JVqUt"
                },
                {
                  "type": "reference",
                  "value": "users/wbMYtNCpwBTfonCznq0h"
                },
                {
                  "type": "reference",
                  "value": "users/Gl4KeQseKlx8vTkr5FsH"
                },
                {
                  "type": "reference",
                  "value": "users/sqXtko2k5VNsgCp5v3e1"
                },
                {
                  "type": "reference",
                  "value": "users/zaBMHUReBXNOp85bBPLC"
                },
                {
                  "type": "reference",
                  "value": "users/C4sxphVmb3XaDc2iGskq"
                }
              ]
            }
          }
        }
      }
    }
  }
}