{
  "type": "object",
  "value": {
    "enrollment-date": {
      "type": "date",
      "value": "2023-11-09T16:03:41.187Z"
    },
    "user-id": {
      "type": "string",
      "value": "PEWHyHacDWYg6xaGbwak"
    },
    "position": {
      "type": "string",
      "value": ""
    },
    "kind-member": {
      "type": "string",
      "value": "player"
    },
    "team-id": {
      "type": "string",
      "value": "ed4uAJzikvLVRCuiS9TI"
    },
    "number": {
      "type": "object",
      "value": {}
    },
    "init-date": {
      "type": "object",
      "value": {}
    },
    "id": {
      "type": "string",
      "value": "BcP5VH1I27ArDw6TM7CA"
    }
  }
}