{
  "type": "object",
  "value": {
    "visibility": {
      "type": "string",
      "value": "protected"
    },
    "kind": {
      "type": "string",
      "value": "api"
    },
    "domain": {
      "type": "string",
      "value": "tournaments"
    },
    "name": {
      "type": "string",
      "value": "UpdateTeamsInGroupUsecase"
    },
    "id": {
      "type": "string",
      "value": "48167c86644447b0a06d"
    },
    "layer": {
      "type": "string",
      "value": "infrastructure"
    }
  }
}