{
  "type": "object",
  "value": {
    "enrollment-date": {
      "type": "date",
      "value": "2023-10-23T19:36:26.368Z"
    },
    "user-id": {
      "type": "string",
      "value": "bI3hTmaXZQw7BPPVmTt4"
    },
    "kind-member": {
      "type": "string",
      "value": "player"
    },
    "team-id": {
      "type": "string",
      "value": "hucJKc5Ii2uZD8GnPVAD"
    },
    "image": {
      "type": "string",
      "value": "teams/hucJKc5Ii2uZD8GnPVAD/members/AiDvDffwJzOzZOAkJ3fV/profile.jpg"
    },
    "number": {
      "type": "number",
      "value": 12
    },
    "init-date": {
      "type": "object",
      "value": {}
    },
    "id": {
      "type": "string",
      "value": "AiDvDffwJzOzZOAkJ3fV"
    },
    "position": {
      "type": "string",
      "value": "Arquero "
    }
  }
}