{
  "type": "object",
  "value": {
    "image": {
      "type": "string",
      "value": ""
    },
    "first-last-name": {
      "type": "string",
      "value": "Gutierrez"
    },
    "second-last-name": {
      "type": "string",
      "value": "Castro"
    },
    "phone": {
      "type": "string",
      "value": ""
    },
    "document": {
      "type": "string",
      "value": "16072828"
    },
    "roles": {
      "type": "Array",
      "value": [
        {
          "type": "string",
          "value": "OmUGOqmXbey71Uys1Em2"
        }
      ]
    },
    "alias": {
      "type": "string",
      "value": ""
    },
    "second-name": {
      "type": "string",
      "value": "Pompilio"
    },
    "id": {
      "type": "string",
      "value": "47fe8851e0534c0fa335"
    },
    "first-name": {
      "type": "string",
      "value": "David"
    },
    "email": {
      "type": "string",
      "value": ""
    },
    "sports-modalities": {
      "type": "object",
      "value": {
        "soccer": {
          "type": "object",
          "value": {}
        }
      }
    }
  }
}