{
  "type": "object",
  "value": {
    "image": {
      "type": "string",
      "value": ""
    },
    "first-last-name": {
      "type": "string",
      "value": "Galvez"
    },
    "second-last-name": {
      "type": "string",
      "value": "Lopez"
    },
    "phone": {
      "type": "string",
      "value": ""
    },
    "document": {
      "type": "string",
      "value": "1053807877"
    },
    "roles": {
      "type": "Array",
      "value": [
        {
          "type": "string",
          "value": "OmUGOqmXbey71Uys1Em2"
        }
      ]
    },
    "alias": {
      "type": "string",
      "value": ""
    },
    "second-name": {
      "type": "string",
      "value": "Edison"
    },
    "id": {
      "type": "string",
      "value": "cc0fdcd80f524ae8bf96"
    },
    "first-name": {
      "type": "string",
      "value": "John"
    },
    "email": {
      "type": "string",
      "value": ""
    },
    "sports-modalities": {
      "type": "object",
      "value": {
        "soccer": {
          "type": "object",
          "value": {}
        }
      }
    }
  }
}