{
  "type": "object",
  "value": {
    "enrollment-date": {
      "type": "date",
      "value": "2023-12-13T04:19:22.981Z"
    },
    "init-date": {
      "type": "date",
      "value": "2023-12-13T04:19:22.981Z"
    },
    "user-id": {
      "type": "string",
      "value": "patdHHESbTYY0IBm3Vll"
    },
    "position": {
      "type": "string",
      "value": ""
    },
    "id": {
      "type": "string",
      "value": "qNnSVrzE47VQSNDWTbhr"
    },
    "kind-member": {
      "type": "string",
      "value": "player"
    },
    "team-id": {
      "type": "string",
      "value": "toynMAmtHxTnMfGYTSo5"
    }
  }
}