{
  "type": "object",
  "value": {
    "enrollment-date": {
      "type": "date",
      "value": "2023-11-08T13:46:00.229Z"
    },
    "init-date": {
      "type": "date",
      "value": "2023-11-08T13:46:00.229Z"
    },
    "user-id": {
      "type": "string",
      "value": "KoZhTDTwKyFNs7NghHej"
    },
    "position": {
      "type": "string",
      "value": ""
    },
    "kind-member": {
      "type": "Array",
      "value": [
        {
          "type": "string",
          "value": "owner"
        },
        {
          "type": "string",
          "value": "technical-director"
        }
      ]
    },
    "team-id": {
      "type": "string",
      "value": "toynMAmtHxTnMfGYTSo5"
    }
  }
}