{
  "type": "object",
  "value": {
    "phone": {
      "type": "string",
      "value": ""
    },
    "document": {
      "type": "string",
      "value": "1054876390"
    },
    "roles": {
      "type": "Array",
      "value": [
        {
          "type": "reference",
          "value": "roles/OmUGOqmXbey71Uys1Em2"
        }
      ]
    },
    "name": {
      "type": "string",
      "value": "Juan Esteban"
    },
    "image": {
      "type": "string",
      "value": ""
    },
    "alias": {
      "type": "string",
      "value": ""
    },
    "email": {
      "type": "string",
      "value": ""
    },
    "last-name": {
      "type": "string",
      "value": "Cardona ríos"
    }
  }
}