{
  "type": "object",
  "value": {
    "enrollment-date": {
      "type": "date",
      "value": "2023-11-08T23:56:41.402Z"
    },
    "init-date": {
      "type": "date",
      "value": "2023-11-08T23:56:41.402Z"
    },
    "user-id": {
      "type": "string",
      "value": "g6OvjqmITeUlMfc7FPRA"
    },
    "position": {
      "type": "string",
      "value": ""
    },
    "id": {
      "type": "string",
      "value": "pkyZXV9C8KJGKe6X6vMb"
    },
    "kind-member": {
      "type": "string",
      "value": "player"
    },
    "team-id": {
      "type": "string",
      "value": "KvXH1k2i83GDJX3Ch78z"
    }
  }
}