{
  "type": "object",
  "value": {
    "image": {
      "type": "string",
      "value": ""
    },
    "first-last-name": {
      "type": "string",
      "value": "Mosquera"
    },
    "second-last-name": {
      "type": "string",
      "value": "Pe\u00f1aloza"
    },
    "phone": {
      "type": "string",
      "value": ""
    },
    "document": {
      "type": "string",
      "value": "1088288456"
    },
    "roles": {
      "type": "Array",
      "value": [
        {
          "type": "string",
          "value": "OmUGOqmXbey71Uys1Em2"
        }
      ]
    },
    "alias": {
      "type": "string",
      "value": ""
    },
    "second-name": {
      "type": "string",
      "value": "Carlos"
    },
    "email": {
      "type": "string",
      "value": ""
    },
    "first-name": {
      "type": "string",
      "value": "Juan"
    },
    "administration-mode": {
      "value": "self-managed",
      "type": "string"
    }
  }
}