{
  "type": "object",
  "value": {
    "enrollment-date": {
      "type": "date",
      "value": "2023-11-08T14:38:48.192Z"
    },
    "init-date": {
      "type": "date",
      "value": "2023-11-08T14:38:48.192Z"
    },
    "user-id": {
      "type": "string",
      "value": "pki8Fmw8ZxdhflL2yqdu"
    },
    "position": {
      "type": "string",
      "value": ""
    },
    "id": {
      "type": "string",
      "value": "MspGnOzgrUci5BIEsDD7"
    },
    "kind-member": {
      "type": "string",
      "value": "player"
    },
    "team-id": {
      "type": "string",
      "value": "toynMAmtHxTnMfGYTSo5"
    }
  }
}