{
  "type": "object",
  "value": {
    "enrollment-date": {
      "type": "date",
      "value": "2023-11-14T16:28:29.009Z"
    },
    "init-date": {
      "type": "date",
      "value": "2023-11-14T16:28:29.009Z"
    },
    "user-id": {
      "type": "string",
      "value": "debGoF8YajPGdIVPcaCC"
    },
    "position": {
      "type": "string",
      "value": ""
    },
    "kind-member": {
      "type": "string",
      "value": "player"
    },
    "team-id": {
      "type": "string",
      "value": "p7oQb7QZiw1nIQoVLwXz"
    }
  }
}