{
  "type": "object",
  "value": {
    "number": {
      "type": "number",
      "value": 23
    },
    "enrollment-date": {
      "type": "date",
      "value": "2023-11-06T22:05:25.186Z"
    },
    "init-date": {
      "type": "date",
      "value": "2023-11-06T22:05:25.186Z"
    },
    "user-id": {
      "type": "string",
      "value": "kzy5QRJGudAuW6PdQgG3"
    },
    "position": {
      "type": "string",
      "value": ""
    },
    "kind-member": {
      "type": "string",
      "value": "player"
    },
    "team-id": {
      "type": "string",
      "value": "AkrAMXCJQzicYVe62ws2"
    }
  }
}