{
  "type": "object",
  "value": {
    "enrollment-date": {
      "type": "date",
      "value": "2023-11-08T14:04:32.210Z"
    },
    "init-date": {
      "type": "date",
      "value": "2023-11-08T14:04:32.210Z"
    },
    "user-id": {
      "type": "string",
      "value": "2SQbYNyr2PcITr7eTnyH"
    },
    "position": {
      "type": "string",
      "value": ""
    },
    "id": {
      "type": "string",
      "value": "Nv2GnZOYE6bDXtN6UFE0"
    },
    "kind-member": {
      "type": "string",
      "value": "player"
    },
    "team-id": {
      "type": "string",
      "value": "JtLHneKRtkuWcdi3y0NH"
    }
  }
}