{
  "type": "object",
  "value": {
    "enrollment-date": {
      "type": "date",
      "value": "2023-11-04T00:50:03.688Z"
    },
    "init-date": {
      "type": "date",
      "value": "2023-11-04T00:50:03.688Z"
    },
    "user-id": {
      "type": "string",
      "value": "UpHowSLO5ESSuzvXFMo7"
    },
    "position": {
      "type": "string",
      "value": ""
    },
    "id": {
      "type": "string",
      "value": "pYJ6YeXvjsFiZqm6Ibfy"
    },
    "kind-member": {
      "type": "string",
      "value": "player"
    },
    "team-id": {
      "type": "string",
      "value": "jgqve2lAcac8T3Ot8kcZ"
    }
  }
}